Metadata-Version: 1.0
Name: Flask-Compass
Version: 0.2
Summary: Adds automatic Compass compilation to Flask
Home-page: https://github.com/zerok/flask-compass
Author: Horst Gutmann
Author-email: zerok@zerokspot.com
License: BSD
Platform: any
Classifier: Environment :: Web Environment
Classifier: Intended Audience :: Developers
Classifier: License :: OSI Approved :: BSD License
Classifier: Operating System :: OS Independent
Classifier: Programming Language :: Python
Classifier: Topic :: Internet :: WWW/HTTP :: Dynamic Content
Classifier: Topic :: Software Development :: Libraries :: Python Modules
